lineages-1.7.data/scripts/lineages
lineages-1.7.dist-info/DESCRIPTION.rst
lineages-1.7.dist-info/METADATA
lineages-1.7.dist-info/RECORD
lineages-1.7.dist-info/WHEEL
lineages-1.7.dist-info/metadata.json
lineages-1.7.dist-info/top_level.txt
src/__init__.py
src/lineages.py
