Metadata-Version: 2.0
Name: lineages
Version: 1.7
Summary: A listing of all the lineages and class rosters of Mobile Developers of Berkeley
Home-page: https://github.com/kevjiangba/FamilyTreeVisualizer
Author: Mobile Developers of Berkeley
Author-email: kevin.jiang@berkeley.edu
License: UNKNOWN
Platform: UNKNOWN
Classifier: Programming Language :: Python :: 3
Classifier: License :: OSI Approved :: MIT License
Classifier: Operating System :: OS Independent
